{"annotatable":{"parts":[]},"anncomplete":false,"sources":[],"metas":{"m_1":{"value":true,"confidence":{"state":"pre-added","who":["user:NLVR"],"prob":1}},"m_2":{"value":"1358-1","confidence":{"state":"pre-added","who":["user:NLVR"],"prob":1}},"m_3":{"value":"60","confidence":{"state":"pre-added","who":["user:NLVR"],"prob":1}},"m_4":{"value":"[[{\"y_loc\":37,\"size\":10,\"type\":\"circle\",\"x_loc\":33,\"color\":\"Yellow\"},{\"y_loc\":90,\"size\":10,\"type\":\"circle\",\"x_loc\":5,\"color\":\"#0099ff\"},{\"y_loc\":59,\"size\":20,\"type\":\"circle\",\"x_loc\":13,\"color\":\"Yellow\"},{\"y_loc\":44,\"size\":10,\"type\":\"triangle\",\"x_loc\":65,\"color\":\"Black\"},{\"y_loc\":23,\"size\":10,\"type\":\"circle\",\"x_loc\":49,\"color\":\"#0099ff\"},{\"y_loc\":19,\"size\":20,\"type\":\"triangle\",\"x_loc\":76,\"color\":\"Yellow\"},{\"y_loc\":90,\"size\":10,\"type\":\"circle\",\"x_loc\":45,\"color\":\"Black\"}],[{\"y_loc\":38,\"size\":30,\"type\":\"circle\",\"x_loc\":66,\"color\":\"Yellow\"}],[{\"y_loc\":12,\"size\":10,\"type\":\"triangle\",\"x_loc\":63,\"color\":\"Black\"}]]","confidence":{"state":"pre-added","who":["user:NLVR"],"prob":1}},"m_5":{"value":"{\"r0\":\"true\"}","confidence":{"state":"pre-added","who":["user:NLVR"],"prob":1}}},"entities":[],"relations":[]}