{"annotatable":{"parts":[]},"anncomplete":false,"sources":[],"metas":{"m_1":{"value":true,"confidence":{"state":"pre-added","who":["user:NLVR"],"prob":1}},"m_2":{"value":"137-0","confidence":{"state":"pre-added","who":["user:NLVR"],"prob":1}},"m_3":{"value":"29","confidence":{"state":"pre-added","who":["user:NLVR"],"prob":1}},"m_4":{"value":"[[{\"y_loc\":70,\"size\":30,\"type\":\"square\",\"x_loc\":40,\"color\":\"Black\"},{\"y_loc\":0,\"size\":30,\"type\":\"square\",\"x_loc\":47,\"color\":\"Black\"},{\"y_loc\":80,\"size\":20,\"type\":\"circle\",\"x_loc\":11,\"color\":\"Black\"},{\"y_loc\":33,\"size\":20,\"type\":\"triangle\",\"x_loc\":77,\"color\":\"Black\"}],[{\"y_loc\":20,\"size\":30,\"type\":\"square\",\"x_loc\":70,\"color\":\"Black\"},{\"y_loc\":10,\"size\":10,\"type\":\"circle\",\"x_loc\":47,\"color\":\"Black\"}],[{\"y_loc\":17,\"size\":10,\"type\":\"triangle\",\"x_loc\":21,\"color\":\"Black\"},{\"y_loc\":52,\"size\":10,\"type\":\"triangle\",\"x_loc\":8,\"color\":\"Yellow\"}]]","confidence":{"state":"pre-added","who":["user:NLVR"],"prob":1}},"m_5":{"value":"{\"r0\":\"true\"}","confidence":{"state":"pre-added","who":["user:NLVR"],"prob":1}}},"entities":[],"relations":[]}